__init__.py
attribute_hashmap.py
gan_evaluator.py
log_utils.py
seed.py
gan_evaluator-1.15.dist-info/LICENSE.md
gan_evaluator-1.15.dist-info/METADATA
gan_evaluator-1.15.dist-info/WHEEL
gan_evaluator-1.15.dist-info/top_level.txt
gan_evaluator-1.15.dist-info/RECORD
