Metadata-Version: 2.1
Name: gan-evaluator
Version: 1.15
Summary: GAN Evaluator for IS and FID
Home-page: https://github.com/ChenLiu-1996/GAN-evaluator
Author: Chen Liu
Author-email: chen.liu.cl2482@yale.edu
License: MIT
Keywords: GAN,evaluator,IS,FID,inception
Platform: UNKNOWN
Requires-Dist: numpy
Requires-Dist: scipy
Requires-Dist: torch
Requires-Dist: torchvision
Requires-Dist: tqdm
